MANIFEST.in
README.md
pygeojs.json
setup.cfg
setup.py
pygeojs/__init__.py
pygeojs/_version.py
pygeojs/example.py
pygeojs/featureLayer.py
pygeojs/featureLayer_autogen.py
pygeojs/feature_autogen.py
pygeojs/layer_autogen.py
pygeojs/osmLayer_autogen.py
pygeojs/pointFeature_autogen.py
pygeojs/scene.py
pygeojs/sceneObject.py
pygeojs/tileLayer.py
pygeojs/tileLayer_autogen.py
pygeojs.egg-info/PKG-INFO
pygeojs.egg-info/SOURCES.txt
pygeojs.egg-info/dependency_links.txt
pygeojs.egg-info/not-zip-safe
pygeojs.egg-info/requires.txt
pygeojs.egg-info/top_level.txt
pygeojs/static/extension.js
pygeojs/static/index.js
pygeojs/static/index.js.map