Metadata-Version: 1.1
Name: pygeojs
Version: 0.1.2
Summary: ipywidget wrapper for GeoJS
Home-page: https://github.com//pygeojs
Author: john Tourtellott
Author-email: john.tourtellott@kitware.com
License: UNKNOWN
Keywords: geojs,ipython,jupyter,widgets
Platform: UNKNOWN
Classifier: Development Status :: 4 - Beta
Classifier: Framework :: IPython
Classifier: Intended Audience :: Developers
Classifier: Intended Audience :: Science/Research
Classifier: Topic :: Multimedia :: Graphics
Classifier: Programming Language :: Python :: 2
Classifier: Programming Language :: Python :: 2.7
Classifier: Programming Language :: Python :: 3
Classifier: Programming Language :: Python :: 3.3
Classifier: Programming Language :: Python :: 3.4
Classifier: Programming Language :: Python :: 3.5
